{
  "project_info": {
    "project_number": "596537174610",
    "firebase_url": "https://fckorea-11ac9.firebaseio.com",
    "project_id": "fckorea-11ac9",
    "storage_bucket": "fckorea-11ac9.appspot.com"
  },
  "client": [
    {
      "client_info": {
        "mobilesdk_app_id": "1:596537174610:android:b3e98de82261b249",
        "android_client_info": {
          "package_name": "com.example.jongkook.firebase_database"
        }
      },
      "oauth_client": [
        {
          "client_id": "596537174610-no73580uu8trl0blc7es0r3ka3sb6eap.apps.googleusercontent.com",
          "client_type": 3
        }
      ],
      "api_key": [
        {
          "current_key": "AIzaSyC-rjStTAvt7GyIupk9uOnEoSrf6bIYvFE"
        }
      ],
      "services": {
        "analytics_service": {
          "status": 1
        },
        "appinvite_service": {
          "status": 1,
          "other_platform_oauth_client": []
        },
        "ads_service": {
          "status": 2
        }
      }
    },
    {
      "client_info": {
        "mobilesdk_app_id": "1:596537174610:android:4f6ef051e817eac4",
        "android_client_info": {
          "package_name": "com.example.jongkook.firebase_message"
        }
      },
      "oauth_client": [
        {
          "client_id": "596537174610-no73580uu8trl0blc7es0r3ka3sb6eap.apps.googleusercontent.com",
          "client_type": 3
        }
      ],
      "api_key": [
        {
          "current_key": "AIzaSyC-rjStTAvt7GyIupk9uOnEoSrf6bIYvFE"
        }
      ],
      "services": {
        "analytics_service": {
          "status": 1
        },
        "appinvite_service": {
          "status": 1,
          "other_platform_oauth_client": []
        },
        "ads_service": {
          "status": 2
        }
      }
    }
  ],
  "configuration_version": "1"
}